{"act_version":"0.1","id":"troubleshooting/webhooks/callback-host-unreachable-symptom","type":"troubleshooting","title":"Callback host unreachable symptom (Webhooks)","summary":"Resolve \"callback host unreachable\" — symptom for the Webhooks surface.","summary_source":"author","content":[{"type":"prose","format":"markdown","text":"## Symptom\n\nAn operation against the Webhooks surface fails with an error matching \"callback host unreachable (symptom)\".\n\n## Resolution\n\n1. Inspect the error envelope.\n2. Re-issue with corrected parameters.\n3. Confirm via the audit log.\n\nSee the [Webhooks API reference](/docs/api/buckets/get) for the exact field set."}],"tokens":{"summary":10,"body":45},"metadata":{"source":{"adapter":"act-docusaurus-sidebar-synthesizer","source_id":"troubleshooting/webhooks/callback-host-unreachable-symptom.md","source_path":"troubleshooting/webhooks/callback-host-unreachable-symptom.md"}},"etag":"s256:iI2uPL9GJOyaorH2Ova786","source":{"human_url":"https://example.com/troubleshooting/webhooks/callback-host-unreachable-symptom/"},"parent":"webhooks-issues"}